{"cameraMode":{"drawMode":0,"name":"Shaded","section":"Shading Mode"},"sceneLighting":true,"audioPlay":false,"sceneViewState":{"showFog":true,"showMaterialUpdate":false,"showSkybox":true,"showFlares":true,"showImageEffects":true,"showParticleSystems":true},"in2DMode":false,"pivot":{"x":2466.12646484375,"y":97.23179626464844,"z":730.2485961914063},"rotation":{"x":0.061111994087696078,"y":-0.9310811758041382,"z":0.1842009574174881,"w":0.3089612126350403},"size":23.927806854248048,"orthographic":false}